flask_sqlalchemy_compat/__init__.py
flask_sqlalchemy_compat/auto.py
flask_sqlalchemy_compat/backdict.py
flask_sqlalchemy_compat/backends.py
flask_sqlalchemy_compat/flask_sa_api.py
flask_sqlalchemy_compat/flask_sa_lite_api.py
flask_sqlalchemy_compat/protocols.py
flask_sqlalchemy_compat/utilities.py
flask_sqlalchemy_compat/version.py
Flask_SQLAlchemy_compat-0.2.2.dist-info/LICENSE
Flask_SQLAlchemy_compat-0.2.2.dist-info/METADATA
Flask_SQLAlchemy_compat-0.2.2.dist-info/WHEEL
Flask_SQLAlchemy_compat-0.2.2.dist-info/top_level.txt
Flask_SQLAlchemy_compat-0.2.2.dist-info/zip-safe
Flask_SQLAlchemy_compat-0.2.2.dist-info/RECORD
